{
  "6062676531fe109865296dc0": {
    "username": "l.have.no.name",
    "joined_at": "2026-07-09T05:08:58.172329",
    "last_seen": "2026-07-09T05:08:58.172329",
    "user_type": "moderator_designer",
    "is_active": true
  },
  "65402b9fffc87c0146e3dcb3": {
    "username": "HR_LY",
    "joined_at": "2026-07-09T05:09:02.132840",
    "last_seen": "2026-07-09T05:09:02.132840",
    "user_type": "bot_developer",
    "is_active": true
  },
  "67f53b4d9d997810968b7179": {
    "username": "M.UM",
    "joined_at": "2026-07-09T05:13:02.364821",
    "last_seen": "2026-07-09T05:13:02.364821",
    "user_type": "visitor",
    "is_active": true
  },
  "6a1d9608004483740949dcae": {
    "username": "S_A_R_A_72",
    "joined_at": "2026-07-09T05:18:38.861333",
    "last_seen": "2026-07-09T05:18:38.861333",
    "user_type": "visitor",
    "is_active": true
  }
}